leet_daily/__init__.py
leet_daily/config.py
leet_daily/leet.py
leet_daily/main.py
leet_daily-0.1.2.dist-info/METADATA
leet_daily-0.1.2.dist-info/WHEEL
leet_daily-0.1.2.dist-info/entry_points.txt
leet_daily-0.1.2.dist-info/RECORD
